{
  "bill": {
    "from_organization": "~{\"classification\": \"lower\"}",
    "identifier": "HB72",
    "legislative_session": "2026",
    "subject": [
      "Appropriations A",
      "Education"
    ],
    "title": "Mississippi Delta Medical Apprenticeship Program (MS DMAP); establish to provide health care career pathways for students in the Delta."
  },
  "id": "HB72",
  "log": {
    "action": {
      "date": "2026-02-03T06:00:00+00:00",
      "description": "Died In Committee",
      "organization_id": "~{\"classification\": \"lower\"}"
    },
    "bill_id": "HB72"
  },
  "sources": {
    "bill": "ms-legislation/country:us/state:ms/sessions/2026/bills/HB72/metadata.json",
    "log": "ms-legislation/country:us/state:ms/sessions/2026/bills/HB72/logs/20260203T060000Z_died_in_committee.json"
  },
  "timestamp": "20260203T060000Z"
}
