{
  "bill": {
    "abstracts": [
      {
        "abstract": "Consumer Protection",
        "note": "full subject"
      }
    ],
    "from_organization": "~{\"classification\": \"lower\"}",
    "identifier": "HB351",
    "legislative_session": "2026rs",
    "subject": [
      "Consumer Protection"
    ],
    "title": "Data privacy; processing of data regulated, consumer actions related to data authorized"
  },
  "id": "HB351",
  "log": {
    "action": {
      "classification": [
        "became-law"
      ],
      "date": "2026-04-17T04:00:00+00:00",
      "description": "Enacted",
      "organization_id": "~{\"classification\": \"lower\"}"
    },
    "bill_id": "HB351"
  },
  "sources": {
    "bill": "al-legislation/country:us/state:al/sessions/2026rs/bills/HB351/metadata.json",
    "log": "al-legislation/country:us/state:al/sessions/2026rs/bills/HB351/logs/20260417T040000Z.classification.became-law.lower.json"
  }
}
